django_generic_follow-0.5.2.dist-info/DESCRIPTION.rst
django_generic_follow-0.5.2.dist-info/METADATA
django_generic_follow-0.5.2.dist-info/RECORD
django_generic_follow-0.5.2.dist-info/WHEEL
django_generic_follow-0.5.2.dist-info/metadata.json
django_generic_follow-0.5.2.dist-info/top_level.txt
generic_follow/__init__.py
generic_follow/managers.py
generic_follow/model_mixins.py
generic_follow/models.py
generic_follow/signals.py
generic_follow/migrations/0001_initial.py
generic_follow/migrations/__init__.py
generic_follow/south_migrations/0001_initial.py
generic_follow/south_migrations/0002_auto__add_unique_follow_user_target_content_type_target_object_id.py
generic_follow/south_migrations/__init__.py
