Metadata-Version: 2.0
Name: django-generic-follow
Version: 0.5.2
Summary: Generic follow system for Django
Home-page: https://github.com/gizmag/django-generic-follow
Author: Gizmag
Author-email: tech@gizmag.com
License: UNKNOWN
Platform: UNKNOWN
Requires-Dist: django (>=1.8)
